.gitignore
.travis.yml
CHANGES.txt
LICENSE.txt
README.rst
setup.cfg
setup.py
docs/Makefile
docs/api-cms.rst
docs/api-directives.rst
docs/api-form.rst
docs/api-interfaces.rst
docs/api-ptah.rst
docs/api-settings.rst
docs/api.rst
docs/authentication.rst
docs/conf.py
docs/content.rst
docs/faq.rst
docs/forms.rst
docs/index.rst
docs/license.rst
docs/manageui.rst
docs/migration.rst
docs/overview.rst
docs/package-structure.rst
docs/populate.rst
docs/ptah_app_vs_manage.rst
docs/rdbms.rst
docs/rest.rst
docs/scripts.rst
docs/startup.rst
docs/tutorial.rst
docs/unique.rst
docs/views.rst
ptah/__init__.py
ptah/authentication.py
ptah/config.py
ptah/events.py
ptah/formatter.py
ptah/interfaces.py
ptah/jsfields.py
ptah/mail.py
ptah/migrate.py
ptah/password.py
ptah/populate.py
ptah/ptahsettings.py
ptah/rst.py
ptah/security.py
ptah/settings.py
ptah/sqla.py
ptah/sqlautils.py
ptah/testing.py
ptah/token.py
ptah/typeinfo.py
ptah/uiactions.py
ptah/uri.py
ptah/util.py
ptah/view.py
ptah.egg-info/PKG-INFO
ptah.egg-info/SOURCES.txt
ptah.egg-info/dependency_links.txt
ptah.egg-info/entry_points.txt
ptah.egg-info/not-zip-safe
ptah.egg-info/requires.txt
ptah.egg-info/top_level.txt
ptah/locale/ptah.pot
ptah/locale/pt_BR/LC_MESSAGES/ptah.mo
ptah/locale/pt_BR/LC_MESSAGES/ptah.po
ptah/manage/__init__.py
ptah/manage/fieldpreviews.py
ptah/manage/fields.py
ptah/manage/introspect.py
ptah/manage/layout.py
ptah/manage/manage.py
ptah/manage/permissions.py
ptah/manage/settings.py
ptah/manage/source.py
ptah/manage/sqla.py
ptah/manage/uri.py
ptah/manage/tests/test_fieldpreviews.py
ptah/manage/tests/test_intr_renderers.py
ptah/manage/tests/test_introspect.py
ptah/manage/tests/test_layout.pt
ptah/manage/tests/test_layout.py
ptah/manage/tests/test_manage.py
ptah/manage/tests/test_permissions.py
ptah/manage/tests/test_settings.py
ptah/manage/tests/test_source.py
ptah/manage/tests/test_sqla.py
ptah/manage/tests/test_uri.py
ptah/scaffolds/__init__.py
ptah/scaffolds/ptah_starter/MANIFEST.in_tmpl
ptah/scaffolds/ptah_starter/settings.ini_tmpl
ptah/scaffolds/ptah_starter/setup.cfg_tmpl
ptah/scaffolds/ptah_starter/setup.py_tmpl
ptah/scaffolds/ptah_starter/+package+/__init__.py_tmpl
