Metadata-Version: 1.1
Name: ptah
Version: 0.8.0
Summary: Ptah is a fast, fun, open source high-level Python web development environment.
Home-page: https://github.com/ptahproject/ptah/
Author: Ptah Project
Author-email: ptahproject@googlegroups.com
License: BSD-derived
Platform: UNKNOWN
Classifier: Intended Audience :: Developers
Classifier: Programming Language :: Python
Classifier: Programming Language :: Python :: 2.6
Classifier: Programming Language :: Python :: 2.7
Classifier: Programming Language :: Python :: 3
Classifier: Programming Language :: Python :: 3.2
Classifier: Programming Language :: Python :: 3.3
Classifier: Programming Language :: Python :: Implementation :: CPython
Classifier: Framework :: Pyramid
Classifier: Topic :: Internet :: WWW/HTTP
Classifier: Topic :: Internet :: WWW/HTTP :: WSGI
